MANIFEST.in
README.rst
setup.py
vander/__init__.py
vander.egg-info/PKG-INFO
vander.egg-info/SOURCES.txt
vander.egg-info/dependency_links.txt
vander.egg-info/entry_points.txt
vander.egg-info/not-zip-safe
vander.egg-info/requires.txt
vander.egg-info/top_level.txt