Metadata-Version: 1.0
Name: vander
Version: 0.1
Summary: Live graphs in your terminal
Home-page: http://github.com/rubzo/vander
Author: Stephen Kyle
Author-email: stephenckyle@gmail.com
License: MIT
Platform: UNKNOWN
